ntnx_files_py_client/__init__.py
ntnx_files_py_client/api_client.py
ntnx_files_py_client/api_response.py
ntnx_files_py_client/configuration.py
ntnx_files_py_client/custom_retry.py
ntnx_files_py_client/rest.py
ntnx_files_py_client/api/__init__.py
ntnx_files_py_client/api/analytics_api.py
ntnx_files_py_client/api/antivirus_servers_api.py
ntnx_files_py_client/api/dns_api.py
ntnx_files_py_client/api/file_servers_api.py
ntnx_files_py_client/api/infected_files_api.py
ntnx_files_py_client/api/mount_targets_api.py
ntnx_files_py_client/api/notification_policies_api.py
ntnx_files_py_client/api/partner_servers_api.py
ntnx_files_py_client/api/quota_policies_api.py
ntnx_files_py_client/api/ransomware_configs_api.py
ntnx_files_py_client/api/recommendations_api.py
ntnx_files_py_client/api/replication_jobs_api.py
ntnx_files_py_client/api/replication_policies_api.py
ntnx_files_py_client/api/snapshot_changed_contents_api.py
ntnx_files_py_client/api/snapshot_schedules_api.py
ntnx_files_py_client/api/snapshots_api.py
ntnx_files_py_client/api/tier_api.py
ntnx_files_py_client/api/unified_namespaces_api.py
ntnx_files_py_client/api/user_mappings_api.py
ntnx_files_py_client/api/virus_scan_policies_api.py
ntnx_files_py_client/models/__init__.py
ntnx_files_py_client/models/OneOfcommon/__init__.py
ntnx_files_py_client/models/OneOfcommon/v1/__init__.py
ntnx_files_py_client/models/OneOfcommon/v1/config/KVPairvalue.py
ntnx_files_py_client/models/OneOfcommon/v1/config/__init__.py
ntnx_files_py_client/models/OneOffiles/__init__.py
ntnx_files_py_client/models/OneOffiles/v4/__init__.py
ntnx_files_py_client/models/OneOffiles/v4/config/CloneMountTargetApiResponsedata.py
ntnx_files_py_client/models/OneOffiles/v4/config/ComputeSnapshotChangeApiResponsedata.py
ntnx_files_py_client/models/OneOffiles/v4/config/CreateAntivirusServerApiResponsedata.py
ntnx_files_py_client/models/OneOffiles/v4/config/CreateMountTargetApiResponsedata.py
ntnx_files_py_client-4.0.1.dist-info/LICENSE.txt
ntnx_files_py_client-4.0.1.dist-info/METADATA
ntnx_files_py_client-4.0.1.dist-info/WHEEL
ntnx_files_py_client-4.0.1.dist-info/top_level.txt
ntnx_files_py_client-4.0.1.dist-info/RECORD
